license
seqviz/__init__.py
seqviz/seqeval.py
seqviz/sequence.py
seqviz/util.py
seqviz-0.1.1.dist-info/license
seqviz-0.1.1.dist-info/WHEEL
seqviz-0.1.1.dist-info/METADATA
seqviz-0.1.1.dist-info/RECORD
