Metadata-Version: 2.1
Name: seqviz
Version: 0.1.1
Summary: seqviz is a Python package to visualize sequence tagging results. It can be either be used to print to console or in Jupyter Notebooks.
Home-page: https://github.com/jcklie/seqviz
License: MIT
Keywords: nlp,deep learning,transformers,sequence tagging,visualization
Author: Jan-Christoph Klie
Author-email: git@mrklie.com
Requires-Python: >=3.8,<4.0
Classifier: Development Status :: 4 - Beta
Classifier: Environment :: Console
Classifier: Environment :: Web Environment
Classifier: Framework :: IPython
Classifier: Framework :: Jupyter
Classifier: License :: OSI Approved :: MIT License
Classifier: Operating System :: OS Independent
Classifier: Programming Language :: Python :: 3
Classifier: Programming Language :: Python :: 3.8
Classifier: Topic :: Scientific/Engineering :: Visualization
Project-URL: Repository, https://github.com/jcklie/seqviz
